pymusicdl/__init__.py
pymusicdl/musicDL.py
pymusicdl/modules/__init__.py
pymusicdl/modules/common.py
pymusicdl/modules/picker.py
pymusicdl/modules/spotify_downloader.py
pymusicdl/modules/ytDownloader.py
pymusicdl-1.5.0.dist-info/LICENSE
pymusicdl-1.5.0.dist-info/METADATA
pymusicdl-1.5.0.dist-info/WHEEL
pymusicdl-1.5.0.dist-info/top_level.txt
pymusicdl-1.5.0.dist-info/RECORD
