Metadata-Version: 2.1
Name: pymusicdl
Version: 1.5.0
Summary: Download spotify and youtube playlists without having to enter any API keys!
Home-page: https://github.com/insaiyancvk/pymusicdl/
Author: C Vamshi Krishna
Author-email: cvamshik1@gmail.com
License: MIT
Keywords: spotify,youtube,music download,music,youtube download,spotify download
Classifier: Development Status :: 5 - Production/Stable
Classifier: Intended Audience :: Developers
Classifier: Topic :: Software Development :: Build Tools
Classifier: License :: OSI Approved :: MIT License
Classifier: Programming Language :: Python :: 3.8
License-File: LICENSE
Requires-Dist: pytube
Requires-Dist: requests
Requires-Dist: rich
Requires-Dist: spotipy
Requires-Dist: urllib3
Requires-Dist: youtube-dl
Requires-Dist: youtube-title-parse
Requires-Dist: yt-dlp
Requires-Dist: windows-curses ; platform_system == "Windows"
